securitygroupie.py
models/SecurityGroup.py
securitygroupie-0.2.dist-info/LICENSE
securitygroupie-0.2.dist-info/METADATA
securitygroupie-0.2.dist-info/WHEEL
securitygroupie-0.2.dist-info/top_level.txt
securitygroupie-0.2.dist-info/RECORD
