Metadata-Version: 2.1
Name: securitygroupie
Version: 0.2
Summary: This tool will find and display Security Groups and their attached resources in an AWS account
Author-email: Jeff Maley <jeffmaley@gmail.com>
License: # MIT License
Project-URL: Homepage, https://github.com/jeffmaley/securitygroupie
Project-URL: Bug Tracker, https://github.com/jeffmaley/securitygroupie/issues
Classifier: Programming Language :: Python :: 3
Classifier: License :: OSI Approved :: MIT License
Classifier: Operating System :: OS Independent
Requires-Python: >=3.7
License-File: LICENSE
